portlandgeneral/__init__.py
portlandgeneral/client.py
portlandgeneral/client_auth.py
portlandgeneral/client_opower.py
portlandgeneral/constants.py
portlandgeneral/queries/__init__.py
portlandgeneral/queries/account_details.py
portlandgeneral/queries/account_dropdown_info.py
portlandgeneral/queries/account_info.py
portlandgeneral/queries/bill_download.py
portlandgeneral/queries/energy_tracker.py
portlandgeneral/responses/__init__.py
portlandgeneral/responses/account_details/__init__.py
portlandgeneral/responses/account_details/account_detail.py
portlandgeneral/responses/account_details/account_detail_list.py
portlandgeneral/responses/account_details/alert.py
portlandgeneral/responses/account_details/alert_details.py
portlandgeneral/responses/account_details/auto_pay_info.py
portlandgeneral/responses/account_details/bill_info.py
portlandgeneral/responses/account_details/current_charges.py
portlandgeneral/responses/account_details/is_paperless_bill_enrollment_response.py
portlandgeneral/responses/account_details/next_bill_info.py
portlandgeneral/responses/account_details/payment_eligibility.py
portlandgeneral/responses/account_details/payment_type_plan_response.py
portlandgeneral/responses/account_details/peak_time_rebate_program_status.py
portlandgeneral/responses/account_details/pending_disconnect_status.py
portlandgeneral/responses/account_details/preferred_due_date.py
portlandgeneral/responses/account_details/preferred_due_date_details.py
portlandgeneral/responses/account_details/renewable_enrollment.py
portlandgeneral/responses/account_details/service_address.py
portlandgeneral/responses/account_details/service_connectivity.py
portlandgeneral/responses/account_details/time_of_day_info.py
portlandgeneral/responses/account_details/tpa_account_detail.py
portlandgeneral/responses/account_details/view_bill_details.py
portlandgeneral/responses/account_info/__init__.py
portlandgeneral/responses/account_info/account_customer.py
portlandgeneral_api-1.2.0.dist-info/LICENSE
portlandgeneral_api-1.2.0.dist-info/METADATA
portlandgeneral_api-1.2.0.dist-info/WHEEL
portlandgeneral_api-1.2.0.dist-info/top_level.txt
portlandgeneral_api-1.2.0.dist-info/RECORD
