Metadata-Version: 2.2
Name: portlandgeneral-api
Version: 1.2.0
Summary: Unofficial Python library for communicating with the Portland General (Electric) API
Home-page: https://github.com/piekstra/portlandgeneral-api
Author: Dev Piekstra
Author-email: piekstra.dev@gmail.com
License: GPL-3
Classifier: Programming Language :: Python :: 3
Classifier: License :: OSI Approved :: GNU General Public License v3 (GPLv3)
Classifier: Operating System :: OS Independent
Requires-Python: >=3.7
License-File: LICENSE
Requires-Dist: requests<3,>=2
Requires-Dist: python-dateutil>=2
Dynamic: author
Dynamic: author-email
Dynamic: classifier
Dynamic: description
Dynamic: description-content-type
Dynamic: home-page
Dynamic: license
Dynamic: requires-dist
Dynamic: requires-python
Dynamic: summary
